downerhelper/__init__.py
downerhelper/gis/__init__.py
downerhelper/gis/gis_functions.py
downerhelper/logicapp/__init__.py
downerhelper/logicapp/send_email.py
downerhelper/logs/__init__.py
downerhelper/logs/postgres_log_queue.py
downerhelper/secrets/__init__.py
downerhelper/secrets/secret_helper.py
downerhelper/sharepoint/__init__.py
downerhelper/sharepoint/sharepoint_functions.py
downerhelper-0.1.25.dist-info/METADATA
downerhelper-0.1.25.dist-info/WHEEL
downerhelper-0.1.25.dist-info/licenses/LICENSE
downerhelper-0.1.25.dist-info/RECORD
