Metadata-Version: 2.4
Name: downerhelper
Version: 0.1.25
Summary: Collection of functions to wrap the Azure SDK
Project-URL: Homepage, https://github.com/DownerEU/geospatialDesign-azure_helper
Author-email: Marcus Oates <marcus.oates@downergroup.com>
License: MIT
License-File: LICENSE
Classifier: License :: OSI Approved :: MIT License
Classifier: Operating System :: OS Independent
Classifier: Programming Language :: Python :: 3
Requires-Python: >=3.8
Requires-Dist: azure-identity==1.18.0
Requires-Dist: azure-keyvault-secrets==4.8.0
Requires-Dist: psycopg2-binary==2.9.9
Requires-Dist: uuid==1.30
